send_telegram_cli/__init__.py
send_telegram_cli/__main__.py
send_telegram_cli/app.py
send_telegram_cli/cli.py
send_telegram_cli-0.0.1.dist-info/LICENSE
send_telegram_cli-0.0.1.dist-info/METADATA
send_telegram_cli-0.0.1.dist-info/WHEEL
send_telegram_cli-0.0.1.dist-info/entry_points.txt
send_telegram_cli-0.0.1.dist-info/top_level.txt
send_telegram_cli-0.0.1.dist-info/RECORD
