Metadata-Version: 2.1
Name: send-telegram-cli
Version: 0.0.1
Summary: Send Telegram Messages and Other files 
Author: Sukhbinder Singh
License: Apache-2.0
Project-URL: Homepage, https://github.com/sukhbinder/send-telegram-cli
Project-URL: Changelog, https://github.com/sukhbinder/send-telegram-cli/releases
Project-URL: Issues, https://github.com/sukhbinder/send-telegram-cli/issues
Project-URL: CI, https://github.com/sukhbinder/send-telegram-cli/actions
Classifier: License :: OSI Approved :: Apache Software License
Requires-Python: >=3.8
License-File: LICENSE
Requires-Dist: click
Provides-Extra: test
Requires-Dist: pytest; extra == "test"
